LICENSE
MANIFEST.in
pyproject.toml
readme.md
src/adjustor/__init__.py
src/adjustor/__main__.py
src/adjustor/events.py
src/adjustor/hhd.py
src/adjustor/i18n.py
src/adjustor/settings.yml
src/adjustor/core/__init__.py
src/adjustor/core/acpi.py
src/adjustor/core/alib.py
src/adjustor/core/const.py
src/adjustor/core/lenovo.py
src/adjustor/core/platform.py
src/adjustor/core/fan/__init__.py
src/adjustor/core/fan/__main__.py
src/adjustor/core/fan/alg.py
src/adjustor/core/fan/core.py
src/adjustor/core/fan/utils.py
src/adjustor/drivers/__init__.py
src/adjustor/drivers/asus/__init__.py
src/adjustor/drivers/asus/settings.yml
src/adjustor/drivers/battery/__init__.py
src/adjustor/drivers/battery/battery.yml
src/adjustor/drivers/general/__init__.py
src/adjustor/drivers/general/settings.yml
src/adjustor/drivers/gpu/__init__.py
src/adjustor/drivers/gpu/power-profiles-daemon.dbus.xml.in
src/adjustor/drivers/gpu/ppd.py
src/adjustor/drivers/gpu/settings.yml
src/adjustor/drivers/lenovo/__init__.py
src/adjustor/drivers/lenovo/settings.yml
src/adjustor/drivers/msi/__init__.py
src/adjustor/drivers/msi/error.yml
src/adjustor/drivers/msi/settings.yml
src/adjustor/drivers/smu/__init__.py
src/adjustor/drivers/smu/qam.yml
src/adjustor/drivers/smu/smu.yml
src/adjustor/fuse/__init__.py
src/adjustor/fuse/gpu.py
src/adjustor/fuse/utils.py
src/hhd/__init__.py
src/hhd/__main__.py
src/hhd/logging.py
src/hhd/sections.yml
src/hhd/settings.yml
src/hhd/utils.py
src/hhd.egg-info/PKG-INFO
src/hhd.egg-info/SOURCES.txt
src/hhd.egg-info/dependency_links.txt
src/hhd.egg-info/entry_points.txt
src/hhd.egg-info/requires.txt
src/hhd.egg-info/top_level.txt
src/hhd/contrib/__init__.py
src/hhd/contrib/__main__.py
src/hhd/contrib/dev.py
src/hhd/contrib/gs.py
src/hhd/contrib/hid_desc.py
src/hhd/contrib/i18n.py
src/hhd/contrib/main.py
src/hhd/contrib/hid_data/0000_undefined.hut
src/hhd/contrib/hid_data/0001_generic_desktop.hut
src/hhd/contrib/hid_data/0002_simulation_controls.hut
src/hhd/contrib/hid_data/0003_vr_controls.hut
src/hhd/contrib/hid_data/0004_sports_controls.hut
src/hhd/contrib/hid_data/0005_gaming_controls.hut
src/hhd/contrib/hid_data/0006_generic_device_controls.hut
