Metadata-Version: 2.4
Name: hhd
Version: 4.1.5
Summary: Handheld Daemon, a tool for configuring handheld devices.
Author-email: Kapenekakis Antheas <pypi@antheas.dev>
License: LGPL-2.1-or-later
Project-URL: Homepage, https://github.com/hhd-dev/hhd
Project-URL: Bug Tracker, https://github.com/hhd-dev/hhd/issues
Classifier: Programming Language :: Python :: 3.10
Classifier: Programming Language :: Python :: 3.11
Classifier: Programming Language :: Python :: 3.12
Classifier: Operating System :: POSIX :: Linux
Requires-Python: >=3.10
License-File: LICENSE
Requires-Dist: evdev>=1.6.1
Requires-Dist: PyYAML>=6.0.1
Requires-Dist: rich>=13.5.2
Requires-Dist: setuptools>=65.5.0
Requires-Dist: python-xlib>=0.33
Requires-Dist: pyserial>=3.5
Requires-Dist: pyroute2>=0.7.3
Requires-Dist: PyGObject>=3.46.0
Requires-Dist: dbus-python>=1.3.2
Dynamic: license-file
